dadapy/__init__.py
dadapy/base.py
dadapy/causal_graph.py
dadapy/clustering.py
dadapy/data.py
dadapy/data_sets.py
dadapy/density_advanced.py
dadapy/density_estimation.py
dadapy/diff_imbalance.py
dadapy/feature_weighting.py
dadapy/hamming.py
dadapy/id_discrete.py
dadapy/id_estimation.py
dadapy/kstar.py
dadapy/metric_comparisons.py
dadapy/neigh_graph.py
dadapy/plot.py
dadapy/_cython/cython_clustering.c
dadapy/_cython/cython_clustering.cpython-311-darwin.so
dadapy/_cython/cython_clustering_v2.c
dadapy/_cython/cython_clustering_v2.cpython-311-darwin.so
dadapy/_cython/cython_density.c
dadapy/_cython/cython_density.cpython-311-darwin.so
dadapy/_cython/cython_differentiable_imbalance.c
dadapy/_cython/cython_differentiable_imbalance.cpython-311-darwin.so
dadapy/_cython/cython_distances.c
dadapy/_cython/cython_distances.cpython-311-darwin.so
dadapy/_cython/cython_grads.c
dadapy/_cython/cython_grads.cpython-311-darwin.so
dadapy/_cython/cython_maximum_likelihood_opt.c
dadapy/_cython/cython_maximum_likelihood_opt.cpython-311-darwin.so
dadapy/_cython/cython_maximum_likelihood_opt_full.c
dadapy/_cython/cython_maximum_likelihood_opt_full.cpython-311-darwin.so
dadapy/_cython/cython_overlap.c
dadapy/_cython/cython_overlap.cpython-311-darwin.so
dadapy/_utils/__init__.py
dadapy/_utils/density_estimation.py
dadapy/_utils/differentiable_imbalance.py
dadapy/_utils/discrete_functions.py
dadapy/_utils/id_estimation.py
dadapy/_utils/metric_comparisons.py
dadapy/_utils/utils.py
dadapy/_utils/discrete_volumes/L_coefficients_exact.dat
dadapy/_utils/discrete_volumes/L_coefficients_float.dat
dadapy/_utils/discrete_volumes/V_exact.dat
dadapy-0.3.3.dist-info/METADATA
dadapy-0.3.3.dist-info/WHEEL
dadapy-0.3.3.dist-info/top_level.txt
dadapy-0.3.3.dist-info/RECORD
