Metadata-Version: 2.4
Name: dadapy
Version: 0.3.3
Summary: Distance-based Analysis of DAta-manifolds in python
Author: DADApy author
License:                                  Apache License
Project-URL: homepage, https://github.com/sissa-data-science/DADApy
Project-URL: documentation, https://dadapy.readthedocs.io/
Project-URL: repository, https://github.com/sissa-data-science/DADApy
Requires-Python: >=3.8
Requires-Dist: numpy<2.0
Requires-Dist: scipy
Requires-Dist: scikit-learn
Requires-Dist: matplotlib
Requires-Dist: seaborn
Requires-Dist: tqdm
Requires-Dist: networkx
Requires-Dist: jax; python_version < "3.9"
Requires-Dist: jax==0.4.30; python_version >= "3.9"
Requires-Dist: jaxlib; python_version < "3.9"
Requires-Dist: jaxlib==0.4.30; python_version >= "3.9"
Requires-Dist: flax==0.8.5; python_version >= "3.9"
Provides-Extra: dev
Requires-Dist: tox; extra == "dev"
Requires-Dist: black; extra == "dev"
Requires-Dist: isort; extra == "dev"
Requires-Dist: pytest; extra == "dev"
